dgi/__init__.py
dgi/base.py
dgi/protocol.py
dgi/utils.py
dgi/docs/Data Gateway Interface User's Guide.pdf
dgi/examples/plot.py
dgi/interfaces/__init__.py
dgi/interfaces/power.py
pydgi-0.1.5.data/scripts/dgi_power_measure.py
pydgi-0.1.5.dist-info/LICENSE
pydgi-0.1.5.dist-info/METADATA
pydgi-0.1.5.dist-info/WHEEL
pydgi-0.1.5.dist-info/top_level.txt
pydgi-0.1.5.dist-info/RECORD
