Metadata-Version: 2.1
Name: pydgi
Version: 0.1.5
Summary: Python implementation for Microchip/Atmel Data Gateway Interface
Home-page: https://github.com/ant9000/pydgi
Author: Antonio Galea
Author-email: antonio.galea@gmail.com
License: UNKNOWN
Platform: UNKNOWN
Classifier: Programming Language :: Python :: 3
Classifier: License :: OSI Approved :: GNU General Public License v3 or later (GPLv3+)
Classifier: Operating System :: OS Independent
Requires-Python: >=3
Requires-Dist: pyusb (>=1)
